datasage_mds-0.0.2.dist-info/licenses/LICENSE
rag_engine/__init__.py
rag_engine/indexing/embedder.py
rag_engine/indexing/index_engine.py
rag_engine/indexing/vector_store.py
rag_engine/ingestion/__init__.py
rag_engine/ingestion/chunker.py
rag_engine/ingestion/loaders.py
rag_engine/retrieval/__init__.py
rag_engine/retrieval/data_models.py
rag_engine/retrieval/generator.py
rag_engine/retrieval/retriever.py
datasage_mds-0.0.2.dist-info/METADATA
datasage_mds-0.0.2.dist-info/WHEEL
datasage_mds-0.0.2.dist-info/top_level.txt
datasage_mds-0.0.2.dist-info/RECORD
