Metadata-Version: 2.4
Name: datasage-mds
Version: 0.0.2
Summary: DATA 533 RAG Engine project with ingestion, indexing, retrieval, and CI
Author-email: Yihang Wang <yihangwang9344@gmail.com>
License: MIT
Requires-Python: >=3.10
License-File: LICENSE
Requires-Dist: sentence-transformers
Requires-Dist: chromadb
Requires-Dist: langchain
Requires-Dist: langchain-community
Requires-Dist: langchain-huggingface
Requires-Dist: pypdf
Dynamic: license-file
